DbStructSync/__init__.py
DbStructSync/cli.py
DbStructSync/db_syns.py
DbStructSync/main_entrance.py
DbStructSync/save_tofiles.py
DbStructSync/test.py
DbStructSync/common/__init__.py
DbStructSync/common/logger.py
DbStructSync/common/mysql_conn.py
DbStructSync/common/parse.py
DbStructSync/common/utils.py
dbstructsync-0.0.3.dist-info/LICENSE
dbstructsync-0.0.3.dist-info/METADATA
dbstructsync-0.0.3.dist-info/WHEEL
dbstructsync-0.0.3.dist-info/top_level.txt
dbstructsync-0.0.3.dist-info/RECORD
